<?xml version='1.0' encoding='utf-8'?>
<TextureAtlas imagePath="BG.png">
<SubTexture name="BG Idle0000" x="0" y="0" width="1280" height="720" frameX="0" frameY="0" frameWidth="1280" frameHeight="720" />
<SubTexture name="BG Idle0001" x="0" y="0" width="1280" height="720" frameX="0" frameY="0" frameWidth="1280" frameHeight="720" />
<SubTexture name="BG Idle0002" x="0" y="0" width="1280" height="720" frameX="0" frameY="0" frameWidth="1280" frameHeight="720" />
<SubTexture name="BG Idle0003" x="1280" y="0" width="1280" height="720" frameX="0" frameY="0" frameWidth="1280" frameHeight="720" />
<SubTexture name="BG Idle0004" x="1280" y="0" width="1280" height="720" frameX="0" frameY="0" frameWidth="1280" frameHeight="720" />
<SubTexture name="BG Idle0005" x="0" y="720" width="1280" height="720" frameX="0" frameY="0" frameWidth="1280" frameHeight="720" />
<SubTexture name="BG Idle0006" x="0" y="720" width="1280" height="720" frameX="0" frameY="0" frameWidth="1280" frameHeight="720" />
<SubTexture name="BG Idle0007" x="1280" y="720" width="1280" height="720" frameX="0" frameY="0" frameWidth="1280" frameHeight="720" />
<SubTexture name="BG Idle0008" x="1280" y="720" width="1280" height="720" frameX="0" frameY="0" frameWidth="1280" frameHeight="720" />
<SubTexture name="BG Idle0009" x="0" y="1440" width="1280" height="720" frameX="0" frameY="0" frameWidth="1280" frameHeight="720" />
<SubTexture name="BG Idle0010" x="0" y="1440" width="1280" height="720" frameX="0" frameY="0" frameWidth="1280" frameHeight="720" />
<SubTexture name="BG Idle0011" x="1280" y="1440" width="1280" height="720" frameX="0" frameY="0" frameWidth="1280" frameHeight="720" />
<SubTexture name="BG Idle0012" x="1280" y="1440" width="1280" height="720" frameX="0" frameY="0" frameWidth="1280" frameHeight="720" />
<SubTexture name="BG Idle0013" x="2560" y="0" width="1280" height="720" frameX="0" frameY="0" frameWidth="1280" frameHeight="720" />
<SubTexture name="BG Idle0014" x="2560" y="0" width="1280" height="720" frameX="0" frameY="0" frameWidth="1280" frameHeight="720" />
<SubTexture name="BG Idle0015" x="2560" y="720" width="1280" height="720" frameX="0" frameY="0" frameWidth="1280" frameHeight="720" />
<SubTexture name="BG Idle0016" x="2560" y="720" width="1280" height="720" frameX="0" frameY="0" frameWidth="1280" frameHeight="720" />
<SubTexture name="BG Idle0017" x="2560" y="1440" width="1280" height="720" frameX="0" frameY="0" frameWidth="1280" frameHeight="720" />
<SubTexture name="BG Idle0018" x="2560" y="1440" width="1280" height="720" frameX="0" frameY="0" frameWidth="1280" frameHeight="720" />
<SubTexture name="BG Idle0019" x="0" y="2160" width="1280" height="720" frameX="0" frameY="0" frameWidth="1280" frameHeight="720" />
<SubTexture name="BG Idle0020" x="0" y="2160" width="1280" height="720" frameX="0" frameY="0" frameWidth="1280" frameHeight="720" />
<SubTexture name="BG Idle0021" x="1280" y="2160" width="1280" height="720" frameX="0" frameY="0" frameWidth="1280" frameHeight="720" />
<SubTexture name="BG Idle0022" x="1280" y="2160" width="1280" height="720" frameX="0" frameY="0" frameWidth="1280" frameHeight="720" />
<SubTexture name="BG Idle0023" x="2560" y="2160" width="1280" height="720" frameX="0" frameY="0" frameWidth="1280" frameHeight="720" />
<SubTexture name="BG Idle0024" x="2560" y="2160" width="1280" height="720" frameX="0" frameY="0" frameWidth="1280" frameHeight="720" />
<SubTexture name="BG Idle0025" x="0" y="2880" width="1280" height="720" frameX="0" frameY="0" frameWidth="1280" frameHeight="720" />
<SubTexture name="BG Idle0026" x="0" y="2880" width="1280" height="720" frameX="0" frameY="0" frameWidth="1280" frameHeight="720" />
<SubTexture name="BG Idle0027" x="1280" y="2880" width="1280" height="720" frameX="0" frameY="0" frameWidth="1280" frameHeight="720" />
<SubTexture name="BG Idle0028" x="1280" y="2880" width="1280" height="720" frameX="0" frameY="0" frameWidth="1280" frameHeight="720" />
<SubTexture name="BG Idle0029" x="2560" y="2880" width="1280" height="720" frameX="0" frameY="0" frameWidth="1280" frameHeight="720" />
<SubTexture name="BG Idle0030" x="2560" y="2880" width="1280" height="720" frameX="0" frameY="0" frameWidth="1280" frameHeight="720" />
<SubTexture name="BG Idle0031" x="3840" y="0" width="1280" height="720" frameX="0" frameY="0" frameWidth="1280" frameHeight="720" />
<SubTexture name="BG Idle0032" x="3840" y="0" width="1280" height="720" frameX="0" frameY="0" frameWidth="1280" frameHeight="720" />
<SubTexture name="BG Idle0033" x="3840" y="720" width="1280" height="720" frameX="0" frameY="0" frameWidth="1280" frameHeight="720" />
<SubTexture name="BG Idle0034" x="3840" y="720" width="1280" height="720" frameX="0" frameY="0" frameWidth="1280" frameHeight="720" />
<SubTexture name="BG Idle0035" x="3840" y="1440" width="1280" height="720" frameX="0" frameY="0" frameWidth="1280" frameHeight="720" />
<SubTexture name="BG Idle0036" x="3840" y="1440" width="1280" height="720" frameX="0" frameY="0" frameWidth="1280" frameHeight="720" />
<SubTexture name="BG Idle0037" x="3840" y="2160" width="1280" height="720" frameX="0" frameY="0" frameWidth="1280" frameHeight="720" />
<SubTexture name="BG Idle0038" x="3840" y="2160" width="1280" height="720" frameX="0" frameY="0" frameWidth="1280" frameHeight="720" />
<SubTexture name="BG Idle0039" x="3840" y="2880" width="1280" height="720" frameX="0" frameY="0" frameWidth="1280" frameHeight="720" />
<SubTexture name="BG Idle0040" x="3840" y="2880" width="1280" height="720" frameX="0" frameY="0" frameWidth="1280" frameHeight="720" />
<SubTexture name="BG Idle0041" x="0" y="3600" width="1280" height="720" frameX="0" frameY="0" frameWidth="1280" frameHeight="720" />
<SubTexture name="BG Idle0042" x="0" y="3600" width="1280" height="720" frameX="0" frameY="0" frameWidth="1280" frameHeight="720" />
<SubTexture name="BG Idle0043" x="1280" y="3600" width="1280" height="720" frameX="0" frameY="0" frameWidth="1280" frameHeight="720" />
<SubTexture name="BG Idle0044" x="1280" y="3600" width="1280" height="720" frameX="0" frameY="0" frameWidth="1280" frameHeight="720" />
<SubTexture name="BG Idle0045" x="2560" y="3600" width="1280" height="720" frameX="0" frameY="0" frameWidth="1280" frameHeight="720" />
<SubTexture name="BG Idle0046" x="2560" y="3600" width="1280" height="720" frameX="0" frameY="0" frameWidth="1280" frameHeight="720" />
<SubTexture name="BG Idle0047" x="3840" y="3600" width="1280" height="720" frameX="0" frameY="0" frameWidth="1280" frameHeight="720" />
<SubTexture name="BG Idle0048" x="3840" y="3600" width="1280" height="720" frameX="0" frameY="0" frameWidth="1280" frameHeight="720" />
<SubTexture name="BG Idle0049" x="0" y="4320" width="1280" height="720" frameX="0" frameY="0" frameWidth="1280" frameHeight="720" />
<SubTexture name="BG Idle0050" x="0" y="4320" width="1280" height="720" frameX="0" frameY="0" frameWidth="1280" frameHeight="720" />
<SubTexture name="BG Idle0051" x="1280" y="4320" width="1280" height="720" frameX="0" frameY="0" frameWidth="1280" frameHeight="720" />
<SubTexture name="BG Idle0052" x="1280" y="4320" width="1280" height="720" frameX="0" frameY="0" frameWidth="1280" frameHeight="720" />
<SubTexture name="BG Idle0053" x="2560" y="4320" width="1280" height="720" frameX="0" frameY="0" frameWidth="1280" frameHeight="720" />
<SubTexture name="BG Idle0054" x="2560" y="4320" width="1280" height="720" frameX="0" frameY="0" frameWidth="1280" frameHeight="720" />
<SubTexture name="BG Idle0055" x="3840" y="4320" width="1280" height="720" frameX="0" frameY="0" frameWidth="1280" frameHeight="720" />
<SubTexture name="BG Idle0056" x="3840" y="4320" width="1280" height="720" frameX="0" frameY="0" frameWidth="1280" frameHeight="720" />
<SubTexture name="BG Idle0057" x="5120" y="0" width="1280" height="720" frameX="0" frameY="0" frameWidth="1280" frameHeight="720" />
<SubTexture name="BG Idle0058" x="5120" y="0" width="1280" height="720" frameX="0" frameY="0" frameWidth="1280" frameHeight="720" />
<SubTexture name="BG Idle0059" x="5120" y="720" width="1280" height="720" frameX="0" frameY="0" frameWidth="1280" frameHeight="720" />
<SubTexture name="BG Idle0060" x="5120" y="720" width="1280" height="720" frameX="0" frameY="0" frameWidth="1280" frameHeight="720" />
<SubTexture name="BG Idle0061" x="5120" y="1440" width="1280" height="720" frameX="0" frameY="0" frameWidth="1280" frameHeight="720" />
<SubTexture name="BG Idle0062" x="5120" y="1440" width="1280" height="720" frameX="0" frameY="0" frameWidth="1280" frameHeight="720" />
<SubTexture name="BG Idle0063" x="5120" y="2160" width="1280" height="720" frameX="0" frameY="0" frameWidth="1280" frameHeight="720" />
<SubTexture name="BG Idle0064" x="5120" y="2160" width="1280" height="720" frameX="0" frameY="0" frameWidth="1280" frameHeight="720" />
<SubTexture name="BG Idle0065" x="5120" y="2880" width="1280" height="720" frameX="0" frameY="0" frameWidth="1280" frameHeight="720" />
<SubTexture name="BG Idle0066" x="5120" y="2880" width="1280" height="720" frameX="0" frameY="0" frameWidth="1280" frameHeight="720" />
<SubTexture name="BG Idle0067" x="5120" y="3600" width="1280" height="720" frameX="0" frameY="0" frameWidth="1280" frameHeight="720" />
<SubTexture name="BG Idle0068" x="5120" y="3600" width="1280" height="720" frameX="0" frameY="0" frameWidth="1280" frameHeight="720" />
<SubTexture name="BG Idle0069" x="5120" y="4320" width="1280" height="720" frameX="0" frameY="0" frameWidth="1280" frameHeight="720" />
<SubTexture name="BG Idle0070" x="5120" y="4320" width="1280" height="720" frameX="0" frameY="0" frameWidth="1280" frameHeight="720" />
<SubTexture name="BG Idle0071" x="0" y="5040" width="1280" height="720" frameX="0" frameY="0" frameWidth="1280" frameHeight="720" />
<SubTexture name="BG Idle0072" x="0" y="5040" width="1280" height="720" frameX="0" frameY="0" frameWidth="1280" frameHeight="720" />
<SubTexture name="BG Idle0073" x="1280" y="5040" width="1280" height="720" frameX="0" frameY="0" frameWidth="1280" frameHeight="720" />
<SubTexture name="BG Idle0074" x="1280" y="5040" width="1280" height="720" frameX="0" frameY="0" frameWidth="1280" frameHeight="720" />
<SubTexture name="BG Idle0075" x="2560" y="5040" width="1280" height="720" frameX="0" frameY="0" frameWidth="1280" frameHeight="720" />
<SubTexture name="BG Idle0076" x="2560" y="5040" width="1280" height="720" frameX="0" frameY="0" frameWidth="1280" frameHeight="720" />
<SubTexture name="BG Idle0077" x="3840" y="5040" width="1280" height="720" frameX="0" frameY="0" frameWidth="1280" frameHeight="720" />
<SubTexture name="BG Idle0078" x="3840" y="5040" width="1280" height="720" frameX="0" frameY="0" frameWidth="1280" frameHeight="720" />
<SubTexture name="BG Idle0079" x="5120" y="5040" width="1280" height="720" frameX="0" frameY="0" frameWidth="1280" frameHeight="720" />
<SubTexture name="BG Idle0080" x="5120" y="5040" width="1280" height="720" frameX="0" frameY="0" frameWidth="1280" frameHeight="720" />
<SubTexture name="BG Idle0081" x="6400" y="0" width="1280" height="720" frameX="0" frameY="0" frameWidth="1280" frameHeight="720" />
<SubTexture name="BG Idle0082" x="6400" y="0" width="1280" height="720" frameX="0" frameY="0" frameWidth="1280" frameHeight="720" />
<SubTexture name="BG Idle0083" x="6400" y="720" width="1280" height="720" frameX="0" frameY="0" frameWidth="1280" frameHeight="720" />
<SubTexture name="BG Idle0084" x="6400" y="720" width="1280" height="720" frameX="0" frameY="0" frameWidth="1280" frameHeight="720" />
<SubTexture name="BG Idle0085" x="6400" y="1440" width="1280" height="720" frameX="0" frameY="0" frameWidth="1280" frameHeight="720" />
<SubTexture name="BG Idle0086" x="6400" y="1440" width="1280" height="720" frameX="0" frameY="0" frameWidth="1280" frameHeight="720" />
<SubTexture name="BG Idle0087" x="6400" y="2160" width="1280" height="720" frameX="0" frameY="0" frameWidth="1280" frameHeight="720" />
<SubTexture name="BG Idle0088" x="6400" y="2160" width="1280" height="720" frameX="0" frameY="0" frameWidth="1280" frameHeight="720" />
<SubTexture name="BG Idle0089" x="6400" y="2880" width="1280" height="720" frameX="0" frameY="0" frameWidth="1280" frameHeight="720" />
<SubTexture name="BG Idle0090" x="6400" y="2880" width="1280" height="720" frameX="0" frameY="0" frameWidth="1280" frameHeight="720" />
<SubTexture name="BG Idle0091" x="6400" y="3600" width="1280" height="720" frameX="0" frameY="0" frameWidth="1280" frameHeight="720" />
<SubTexture name="BG Idle0092" x="6400" y="3600" width="1280" height="720" frameX="0" frameY="0" frameWidth="1280" frameHeight="720" />
</TextureAtlas>
